{
	"ident": 1086,
	"order": 11,
	"objtype": "kComponent",
	"componentlib": "jsCheckbox",
	"componentctrl": "Checkbox Control",
	"properties": {
		"alpha": 255,
		"backalpha": 0,
		"backcolor": "RGB(255,255,255)",
		"bordercolor": "kColorDefault",
		"contextmenu": "",
		"cssclassname": "",
		"dataname": "ibDoNotImportFirstLine",
		"desgroup": 0,
		"designactive": true,
		"deslock": false,
		"disabledefaultcontextmenu": false,
		"disablesystemfocus": false,
		"dropmode": "kAcceptNone",
		"effect": "kJSborderNone",
		"enabled": true,
		"events": "evClick",
		"fieldstyle": "",
		"font": 1,
		"fontsize": 10,
		"fontstyle": "kPlain",
		"iconid": 0,
		"linestyle": 1,
		"objlink": 65567,
		"preventlayoutanimation": false,
		"text": "",
		"textcolor": "kColorDefault",
		"tooltip": "",
		"userinfo": "",
		"visible": true
	},
	"screensizes": [
		{
			"name": "kSSZDesktop",
			"left": 788,
			"top": 229,
			"width": 27,
			"height": 30,
			"edgefloat": "kEFnone",
			"dragborder": false,
			"errortextpos": "kJSErrorTextPosUnder"
		}
	]
}
