[
	{
		"name": "$construct",
		"ident": 1,
		"order": 1,
		"pvardefs": [

		],
		"lvardefs": [
			{
				"name": "lbProceed",
				"order": 1,
				"type": "kBoolean",
				"subtype": 0,
				"sublen": 0
			}
		]
	},
	{
		"name": "$destruct",
		"ident": 2,
		"order": 2,
		"pvardefs": [

		],
		"lvardefs": [
			{
				"name": "lbProceed",
				"order": 1,
				"type": "kBoolean",
				"subtype": 0,
				"sublen": 0
			}
		]
	},
	{
		"name": "$Refresh",
		"ident": 0,
		"order": 3,
		"pvardefs": [

		],
		"lvardefs": [
			{
				"name": "lbOK",
				"order": 2,
				"type": "kBoolean",
				"subtype": 0,
				"sublen": 0
			},
			{
				"name": "lRow",
				"order": 1,
				"type": "kRow",
				"subtype": "",
				"sublen": 0
			}
		]
	},
	{
		"name": "$behaviour",
		"ident": 3,
		"order": 4,
		"pvardefs": [

		],
		"lvardefs": [

		],
		"empty": true
	},
	{
		"name": "$event",
		"ident": 4,
		"order": 5,
		"pvardefs": [

		],
		"lvardefs": [

		]
	},
	{
		"name": "$Save",
		"ident": 5,
		"order": 6,
		"pvardefs": [

		],
		"lvardefs": [
			{
				"name": "lbOK",
				"order": 2,
				"type": "kBoolean",
				"subtype": 0,
				"sublen": 0
			},
			{
				"name": "lRow",
				"order": 1,
				"type": "kRow",
				"subtype": "",
				"sublen": 0
			}
		]
	},
	{
		"name": "$GetData",
		"ident": 6,
		"order": 7,
		"pvardefs": [

		],
		"lvardefs": [

		]
	},
	{
		"name": "--- COPYRIGHT ---",
		"ident": 7,
		"order": 8,
		"pvardefs": [

		],
		"lvardefs": [

		]
	}
]
